frameworkjs/__init__.py
frameworkjs/base_page.py
frameworkjs/logger.py
frameworkjs-0.1.0.dist-info/METADATA
frameworkjs-0.1.0.dist-info/WHEEL
frameworkjs-0.1.0.dist-info/top_level.txt
frameworkjs-0.1.0.dist-info/RECORD
