Metadata-Version: 2.4
Name: frameworkjs
Version: 0.1.0
Summary: Reusable Selenium BasePage for Pytest automation
Author: Maulik Patel
Classifier: Programming Language :: Python :: 3
Classifier: Framework :: Pytest
Classifier: Operating System :: OS Independent
Requires-Python: >=3.6
Requires-Dist: selenium>=4.0.0
Dynamic: author
Dynamic: classifier
Dynamic: requires-dist
Dynamic: requires-python
Dynamic: summary
